wptserve/__init__.py
wptserve/config.py
wptserve/constants.py
wptserve/handlers.py
wptserve/logger.py
wptserve/pipes.py
wptserve/ranges.py
wptserve/request.py
wptserve/response.py
wptserve/router.py
wptserve/routes.py
wptserve/server.py
wptserve/stash.py
wptserve/utils.py
wptserve/wptserve.py
wptserve/ws_h2_handshake.py
wptserve/cgi/__init__.py
wptserve/cgi/cgi.py
wptserve/cgi/test_cgi.py
wptserve/sslutils/__init__.py
wptserve/sslutils/base.py
wptserve/sslutils/openssl.py
wptserve/sslutils/pregenerated.py
wptserve-4.0.3.dist-info/METADATA
wptserve-4.0.3.dist-info/WHEEL
wptserve-4.0.3.dist-info/top_level.txt
wptserve-4.0.3.dist-info/RECORD
