Metadata-Version: 2.4
Name: wptserve
Version: 4.0.3
Summary: Python web server intended for in web browser testing
Home-page: http://wptserve.readthedocs.org/
Author: James Graham
Author-email: james@hoppipolla.co.uk
License: BSD
Classifier: Development Status :: 5 - Production/Stable
Classifier: License :: OSI Approved :: BSD License
Classifier: Topic :: Internet :: WWW/HTTP :: HTTP Servers
Requires-Dist: h2>=4.1.0
Requires-Dist: pywebsocket3>=4.0.2
Dynamic: author
Dynamic: author-email
Dynamic: classifier
Dynamic: description
Dynamic: home-page
Dynamic: keywords
Dynamic: license
Dynamic: requires-dist
Dynamic: summary
